{
  "doors": [],
  "metadata": {
    "schema": "1.0.0",
    "agent": {
      "horizon": 30,
      "position": {
        "x": 0.25,
        "y": 0.95,
        "z": 0.25
      },
      "rotation": {
        "x": 0,
        "y": 0,
        "z": 0
      },
      "standing": true
    },
    "agentPoses": {
      "default": {
        "horizon": 30,
        "position": {
          "x": 0.25,
          "y": 0.95,
          "z": 0.25
        },
        "rotation": {
          "x": 0,
          "y": 0,
          "z": 0
        },
        "standing": true
      },
      "arm": {
        "horizon": 30,
        "position": {
          "x": 0.25,
          "y": 0.95,
          "z": 0.25
        },
        "rotation": {
          "x": 0,
          "y": 0,
          "z": 0
        },
        "standing": true
      },
      "locobot": {
        "horizon": 30,
        "position": {
          "x": 0.25,
          "y": 0.95,
          "z": 0.25
        },
        "rotation": {
          "x": 0,
          "y": 0,
          "z": 0
        },
        "standing": null
      },
      "stretch": {
        "horizon": 30,
        "position": {
          "x": 0.25,
          "y": 0.95,
          "z": 0.25
        },
        "rotation": {
          "x": 0,
          "y": 0,
          "z": 0
        },
        "standing": true
      }
    }
  },
  "objects": [],
  "proceduralParameters": {
    "floorColliderThickness": 1.0,
    "receptacleHeight": 0.7,
    "skyboxId": "Sky1",
    "ceilingMaterial": {
      "name": "PureWhite"
    },
    "lights": [
      {
        "id": "DirectionalLight",
        "type": "directional",
        "intensity": 1.0,
        "indirectMultiplier": 1.0,
        "position": {
          "x": 0.84,
          "y": 0.1855,
          "z": -1.09
        },
        "rotation": {
          "x": 66,
          "y": 75,
          "z": 0
        },
        "rgb": {
          "r": 1.0,
          "g": 1.0,
          "b": 1.0
        },
        "shadow": {
          "type": "Soft",
          "strength": 1,
          "normalBias": 0,
          "bias": 0,
          "nearPlane": 0.2,
          "resolution": "FromQualitySettings"
        }
      }
    ]
  },
  "rooms": [
    {
      "id": "room|0",
      "roomType": "Bedroom",
      "children": [],
      "ceilings": [],
      "floorMaterial": {
        "name": "WoodFloorsCross"
      },
      "floorPolygon": [
        {
          "x": -0.5,
          "y": 0,
          "z": -0.5
        },
        {
          "x": -0.5,
          "y": 0,
          "z": 3.901261940598488
        },
        {
          "x": 4.115214467048645,
          "y": 0,
          "z": 3.901261940598488
        },
        {
          "x": 4.115214467048645,
          "y": 0,
          "z": -0.5
        }
      ]
    }
  ],
  "walls": [
    {
      "id": "wall|0|0.00|0.00|0.00|3.40",
      "roomId": "room|0",
      "color": {
        "r": 1.0,
        "g": 1.0,
        "b": 1.0
      },
      "material": {
        "name": "PureWhite",
        "color": {
          "r": 1.0,
          "g": 1.0,
          "b": 1.0
        }
      },
      "polygon": [
        {
          "x": 0.0,
          "y": 0,
          "z": 0.0
        },
        {
          "x": 0.0,
          "y": 0,
          "z": 3.401261940598488
        },
        {
          "x": 0.0,
          "y": 3,
          "z": 3.401261940598488
        },
        {
          "x": 0.0,
          "y": 3,
          "z": 0.0
        }
      ]
    },
    {
      "id": "wall|0|0.00|3.40|3.62|3.40",
      "roomId": "room|0",
      "color": {
        "r": 1.0,
        "g": 1.0,
        "b": 1.0
      },
      "material": {
        "name": "PureWhite",
        "color": {
          "r": 1.0,
          "g": 1.0,
          "b": 1.0
        }
      },
      "polygon": [
        {
          "x": 0.0,
          "y": 0,
          "z": 3.401261940598488
        },
        {
          "x": 3.615214467048645,
          "y": 0,
          "z": 3.401261940598488
        },
        {
          "x": 3.615214467048645,
          "y": 3,
          "z": 3.401261940598488
        },
        {
          "x": 0.0,
          "y": 3,
          "z": 3.401261940598488
        }
      ]
    },
    {
      "id": "wall|0|3.62|3.40|3.62|0.00",
      "roomId": "room|0",
      "color": {
        "r": 1.0,
        "g": 1.0,
        "b": 1.0
      },
      "material": {
        "name": "PureWhite",
        "color": {
          "r": 1.0,
          "g": 1.0,
          "b": 1.0
        }
      },
      "polygon": [
        {
          "x": 3.615214467048645,
          "y": 0,
          "z": 3.401261940598488
        },
        {
          "x": 3.615214467048645,
          "y": 0,
          "z": 0.0
        },
        {
          "x": 3.615214467048645,
          "y": 3,
          "z": 0.0
        },
        {
          "x": 3.615214467048645,
          "y": 3,
          "z": 3.401261940598488
        }
      ]
    },
    {
      "id": "wall|0|3.62|0.00|0.00|0.00",
      "roomId": "room|0",
      "color": {
        "r": 1.0,
        "g": 1.0,
        "b": 1.0
      },
      "material": {
        "name": "PureWhite",
        "color": {
          "r": 1.0,
          "g": 1.0,
          "b": 1.0
        }
      },
      "polygon": [
        {
          "x": 3.615214467048645,
          "y": 0,
          "z": 0.0
        },
        {
          "x": 0.0,
          "y": 0,
          "z": 0.0
        },
        {
          "x": 0.0,
          "y": 3,
          "z": 0.0
        },
        {
          "x": 3.615214467048645,
          "y": 3,
          "z": 0.0
        }
      ]
    },
    {
      "id": "furn|0|0",
      "roomId": "room|0",
      "material": {
        "name": "PureWhite"
      },
      "polygon": [
        {
          "x": 1.8299541520756686,
          "y": 2.1444455683231354,
          "z": 0.6091319818200829
        },
        {
          "x": 1.8308211691346348,
          "y": 2.1444455683231354,
          "z": 1.210154374814013
        },
        {
          "x": 1.8308211691346348,
          "y": 3.0,
          "z": 1.210154374814013
        },
        {
          "x": 1.8299541520756686,
          "y": 3.0,
          "z": 0.6091319818200829
        }
      ]
    },
    {
      "id": "furn|0|1",
      "roomId": "room|0",
      "material": {
        "name": "PureWhite"
      },
      "polygon": [
        {
          "x": 1.8308211691346348,
          "y": 2.1444455683231354,
          "z": 1.210154374814013
        },
        {
          "x": 2.4203586531001124,
          "y": 2.1444455683231354,
          "z": 1.2093039255438087
        },
        {
          "x": 2.4203586531001124,
          "y": 3.0,
          "z": 1.2093039255438087
        },
        {
          "x": 1.8308211691346348,
          "y": 3.0,
          "z": 1.210154374814013
        }
      ]
    },
    {
      "id": "furn|0|2",
      "roomId": "room|0",
      "material": {
        "name": "PureWhite"
      },
      "polygon": [
        {
          "x": 2.4203586531001124,
          "y": 2.1444455683231354,
          "z": 1.2093039255438087
        },
        {
          "x": 2.4194916360411463,
          "y": 2.1444455683231354,
          "z": 0.6082815325498787
        },
        {
          "x": 2.4194916360411463,
          "y": 3.0,
          "z": 0.6082815325498787
        },
        {
          "x": 2.4203586531001124,
          "y": 3.0,
          "z": 1.2093039255438087
        }
      ]
    },
    {
      "id": "furn|0|3",
      "roomId": "room|0",
      "material": {
        "name": "PureWhite"
      },
      "polygon": [
        {
          "x": 2.4194916360411463,
          "y": 2.1444455683231354,
          "z": 0.6082815325498787
        },
        {
          "x": 1.8299541520756686,
          "y": 2.1444455683231354,
          "z": 0.6091319818200829
        },
        {
          "x": 1.8299541520756686,
          "y": 3.0,
          "z": 0.6091319818200829
        },
        {
          "x": 2.4194916360411463,
          "y": 3.0,
          "z": 0.6082815325498787
        }
      ]
    },
    {
      "id": "furn|0|lid",
      "roomId": "room|0",
      "material": {
        "name": "PureWhite"
      },
      "polygon": [
        {
          "x": 1.8299541520756686,
          "y": 3.0,
          "z": 0.6091319818200829
        },
        {
          "x": 2.4194916360411463,
          "y": 3.0,
          "z": 0.6082815325498787
        },
        {
          "x": 2.4203586531001124,
          "y": 3.0,
          "z": 1.2093039255438087
        },
        {
          "x": 1.8308211691346348,
          "y": 3.0,
          "z": 1.210154374814013
        }
      ]
    },
    {
      "id": "furn|1|0",
      "roomId": "room|0",
      "material": {
        "name": "PureWhite"
      },
      "polygon": [
        {
          "x": 1.3935152729431195,
          "y": 0.0,
          "z": 2.1284521218052515
        },
        {
          "x": 3.5545491400236013,
          "y": 0.0,
          "z": 2.128538070857707
        },
        {
          "x": 3.5545491400236013,
          "y": 3.0,
          "z": 2.128538070857707
        },
        {
          "x": 1.3935152729431195,
          "y": 3.0,
          "z": 2.1284521218052515
        }
      ]
    },
    {
      "id": "furn|1|1",
      "roomId": "room|0",
      "material": {
        "name": "PureWhite"
      },
      "polygon": [
        {
          "x": 3.5545491400236013,
          "y": 0.0,
          "z": 2.128538070857707
        },
        {
          "x": 3.5546325007995563,
          "y": 0.0,
          "z": 0.03258174698442146
        },
        {
          "x": 3.5546325007995563,
          "y": 3.0,
          "z": 0.03258174698442146
        },
        {
          "x": 3.5545491400236013,
          "y": 3.0,
          "z": 2.128538070857707
        }
      ]
    },
    {
      "id": "furn|1|2",
      "roomId": "room|0",
      "material": {
        "name": "PureWhite"
      },
      "polygon": [
        {
          "x": 3.5546325007995563,
          "y": 0.0,
          "z": 0.03258174698442146
        },
        {
          "x": 1.3935986337190744,
          "y": 0.0,
          "z": 0.03249579793196571
        },
        {
          "x": 1.3935986337190744,
          "y": 3.0,
          "z": 0.03249579793196571
        },
        {
          "x": 3.5546325007995563,
          "y": 3.0,
          "z": 0.03258174698442146
        }
      ]
    },
    {
      "id": "furn|1|3",
      "roomId": "room|0",
      "material": {
        "name": "PureWhite"
      },
      "polygon": [
        {
          "x": 1.3935986337190744,
          "y": 0.0,
          "z": 0.03249579793196571
        },
        {
          "x": 1.3935152729431195,
          "y": 0.0,
          "z": 2.1284521218052515
        },
        {
          "x": 1.3935152729431195,
          "y": 3.0,
          "z": 2.1284521218052515
        },
        {
          "x": 1.3935986337190744,
          "y": 3.0,
          "z": 0.03249579793196571
        }
      ]
    },
    {
      "id": "furn|1|lid",
      "roomId": "room|0",
      "material": {
        "name": "PureWhite"
      },
      "polygon": [
        {
          "x": 1.3935152729431195,
          "y": 3.0,
          "z": 2.1284521218052515
        },
        {
          "x": 1.3935986337190744,
          "y": 3.0,
          "z": 0.03249579793196571
        },
        {
          "x": 3.5546325007995563,
          "y": 3.0,
          "z": 0.03258174698442146
        },
        {
          "x": 3.5545491400236013,
          "y": 3.0,
          "z": 2.128538070857707
        }
      ]
    },
    {
      "id": "furn|2|0",
      "roomId": "room|0",
      "material": {
        "name": "PureWhite"
      },
      "polygon": [
        {
          "x": 3.614704549968244,
          "y": 0.0,
          "z": 3.4053881474846226
        },
        {
          "x": 3.6157147855137994,
          "y": 0.0,
          "z": 2.9710516765817023
        },
        {
          "x": 3.6157147855137994,
          "y": 3.0,
          "z": 2.9710516765817023
        },
        {
          "x": 3.614704549968244,
          "y": 3.0,
          "z": 3.4053881474846226
        }
      ]
    },
    {
      "id": "furn|2|1",
      "roomId": "room|0",
      "material": {
        "name": "PureWhite"
      },
      "polygon": [
        {
          "x": 3.6157147855137994,
          "y": 0.0,
          "z": 2.9710516765817023
        },
        {
          "x": 0.06720119649171721,
          "y": 0.0,
          "z": 2.962798087943234
        },
        {
          "x": 0.06720119649171721,
          "y": 3.0,
          "z": 2.962798087943234
        },
        {
          "x": 3.6157147855137994,
          "y": 3.0,
          "z": 2.9710516765817023
        }
      ]
    },
    {
      "id": "furn|2|2",
      "roomId": "room|0",
      "material": {
        "name": "PureWhite"
      },
      "polygon": [
        {
          "x": 0.06720119649171721,
          "y": 0.0,
          "z": 2.962798087943234
        },
        {
          "x": 0.0661909609461617,
          "y": 0.0,
          "z": 3.397134558846154
        },
        {
          "x": 0.0661909609461617,
          "y": 3.0,
          "z": 3.397134558846154
        },
        {
          "x": 0.06720119649171721,
          "y": 3.0,
          "z": 2.962798087943234
        }
      ]
    },
    {
      "id": "furn|2|3",
      "roomId": "room|0",
      "material": {
        "name": "PureWhite"
      },
      "polygon": [
        {
          "x": 0.0661909609461617,
          "y": 0.0,
          "z": 3.397134558846154
        },
        {
          "x": 3.614704549968244,
          "y": 0.0,
          "z": 3.4053881474846226
        },
        {
          "x": 3.614704549968244,
          "y": 3.0,
          "z": 3.4053881474846226
        },
        {
          "x": 0.0661909609461617,
          "y": 3.0,
          "z": 3.397134558846154
        }
      ]
    },
    {
      "id": "furn|2|lid",
      "roomId": "room|0",
      "material": {
        "name": "PureWhite"
      },
      "polygon": [
        {
          "x": 3.614704549968244,
          "y": 3.0,
          "z": 3.4053881474846226
        },
        {
          "x": 0.0661909609461617,
          "y": 3.0,
          "z": 3.397134558846154
        },
        {
          "x": 0.06720119649171721,
          "y": 3.0,
          "z": 2.962798087943234
        },
        {
          "x": 3.6157147855137994,
          "y": 3.0,
          "z": 2.9710516765817023
        }
      ]
    },
    {
      "id": "furn|3|0",
      "roomId": "room|0",
      "material": {
        "name": "PureWhite"
      },
      "polygon": [
        {
          "x": 0.9846773321256681,
          "y": 0.0,
          "z": 0.13532070252928755
        },
        {
          "x": 0.5056506888377816,
          "y": 0.0,
          "z": 0.13709349658341294
        },
        {
          "x": 0.5056506888377816,
          "y": 3.0,
          "z": 0.13709349658341294
        },
        {
          "x": 0.9846773321256681,
          "y": 3.0,
          "z": 0.13532070252928755
        }
      ]
    },
    {
      "id": "furn|3|1",
      "roomId": "room|0",
      "material": {
        "name": "PureWhite"
      },
      "polygon": [
        {
          "x": 0.5056506888377816,
          "y": 0.0,
          "z": 0.13709349658341294
        },
        {
          "x": 0.511186582364078,
          "y": 0.0,
          "z": 1.6329471674200533
        },
        {
          "x": 0.511186582364078,
          "y": 3.0,
          "z": 1.6329471674200533
        },
        {
          "x": 0.5056506888377816,
          "y": 3.0,
          "z": 0.13709349658341294
        }
      ]
    },
    {
      "id": "furn|3|2",
      "roomId": "room|0",
      "material": {
        "name": "PureWhite"
      },
      "polygon": [
        {
          "x": 0.511186582364078,
          "y": 0.0,
          "z": 1.6329471674200533
        },
        {
          "x": 0.9902132256519645,
          "y": 0.0,
          "z": 1.6311743733659279
        },
        {
          "x": 0.9902132256519645,
          "y": 3.0,
          "z": 1.6311743733659279
        },
        {
          "x": 0.511186582364078,
          "y": 3.0,
          "z": 1.6329471674200533
        }
      ]
    },
    {
      "id": "furn|3|3",
      "roomId": "room|0",
      "material": {
        "name": "PureWhite"
      },
      "polygon": [
        {
          "x": 0.9902132256519645,
          "y": 0.0,
          "z": 1.6311743733659279
        },
        {
          "x": 0.9846773321256681,
          "y": 0.0,
          "z": 0.13532070252928755
        },
        {
          "x": 0.9846773321256681,
          "y": 3.0,
          "z": 0.13532070252928755
        },
        {
          "x": 0.9902132256519645,
          "y": 3.0,
          "z": 1.6311743733659279
        }
      ]
    },
    {
      "id": "furn|3|lid",
      "roomId": "room|0",
      "material": {
        "name": "PureWhite"
      },
      "polygon": [
        {
          "x": 0.9846773321256681,
          "y": 3.0,
          "z": 0.13532070252928755
        },
        {
          "x": 0.9902132256519645,
          "y": 3.0,
          "z": 1.6311743733659279
        },
        {
          "x": 0.511186582364078,
          "y": 3.0,
          "z": 1.6329471674200533
        },
        {
          "x": 0.5056506888377816,
          "y": 3.0,
          "z": 0.13709349658341294
        }
      ]
    }
  ],
  "windows": [],
  "furniture_boxes": [
    [
      1.3935152729431195,
      3.5546325007995563,
      0.03249579793196571,
      2.128538070857707
    ],
    [
      0.0661909609461617,
      3.6157147855137994,
      2.962798087943234,
      3.4053881474846226
    ],
    [
      0.5056506888377816,
      0.9902132256519645,
      0.13532070252928755,
      1.6329471674200533
    ]
  ],
  "room_dims": {
    "l": 3.615214467048645,
    "w": 3.401261940598488
  },
  "objects_raw": [
    {
      "class": "lamp",
      "size": {
        "x": 0.5895380973815918,
        "y": 0.5431267619132996,
        "z": 0.6010230183601379
      },
      "position": {
        "x": 0.3034186363220215,
        "y": 2.416008949279785,
        "z": -0.716036319732666
      },
      "rotation": {
        "x": 0,
        "y": -0.0014425693079829216,
        "z": 0
      }
    },
    {
      "class": "bed",
      "size": {
        "x": 2.095956325531006,
        "y": 1.1237713098526,
        "z": 2.161033868789673
      },
      "position": {
        "x": 0.6523361206054688,
        "y": -0.00048201531171798706,
        "z": -0.5447373390197754
      },
      "rotation": {
        "x": 0,
        "y": -1.5707565546035767,
        "z": 0
      }
    },
    {
      "class": "bookshelf",
      "size": {
        "x": 3.548523187637329,
        "y": 2.5364830493927,
        "z": 0.43433764576911926
      },
      "position": {
        "x": 0.019215106964111328,
        "y": 0.0035118297673761845,
        "z": 1.5588388442993164
      },
      "rotation": {
        "x": 0,
        "y": -3.1392667293548584,
        "z": 0
      }
    },
    {
      "class": "wardrobe",
      "size": {
        "x": 1.495863914489746,
        "y": 1.9398174285888672,
        "z": 0.47902992367744446
      },
      "position": {
        "x": -1.073805809020996,
        "y": 0.004053306300193071,
        "z": -0.7411203384399414
      },
      "rotation": {
        "x": 0,
        "y": 1.5670955181121826,
        "z": 0
      }
    }
  ]
}