{
  "doors": [],
  "metadata": {
    "schema": "1.0.0",
    "agent": {
      "horizon": 30,
      "position": {
        "x": 0.25,
        "y": 0.95,
        "z": 0.25
      },
      "rotation": {
        "x": 0,
        "y": 0,
        "z": 0
      },
      "standing": true
    },
    "agentPoses": {
      "default": {
        "horizon": 30,
        "position": {
          "x": 0.25,
          "y": 0.95,
          "z": 0.25
        },
        "rotation": {
          "x": 0,
          "y": 0,
          "z": 0
        },
        "standing": true
      },
      "arm": {
        "horizon": 30,
        "position": {
          "x": 0.25,
          "y": 0.95,
          "z": 0.25
        },
        "rotation": {
          "x": 0,
          "y": 0,
          "z": 0
        },
        "standing": true
      },
      "locobot": {
        "horizon": 30,
        "position": {
          "x": 0.25,
          "y": 0.95,
          "z": 0.25
        },
        "rotation": {
          "x": 0,
          "y": 0,
          "z": 0
        },
        "standing": null
      },
      "stretch": {
        "horizon": 30,
        "position": {
          "x": 0.25,
          "y": 0.95,
          "z": 0.25
        },
        "rotation": {
          "x": 0,
          "y": 0,
          "z": 0
        },
        "standing": true
      }
    }
  },
  "objects": [],
  "proceduralParameters": {
    "floorColliderThickness": 1.0,
    "receptacleHeight": 0.7,
    "skyboxId": "Sky1",
    "ceilingMaterial": {
      "name": "PureWhite"
    },
    "lights": [
      {
        "id": "DirectionalLight",
        "type": "directional",
        "intensity": 1.0,
        "indirectMultiplier": 1.0,
        "position": {
          "x": 0.84,
          "y": 0.1855,
          "z": -1.09
        },
        "rotation": {
          "x": 66,
          "y": 75,
          "z": 0
        },
        "rgb": {
          "r": 1.0,
          "g": 1.0,
          "b": 1.0
        },
        "shadow": {
          "type": "Soft",
          "strength": 1,
          "normalBias": 0,
          "bias": 0,
          "nearPlane": 0.2,
          "resolution": "FromQualitySettings"
        }
      }
    ]
  },
  "rooms": [
    {
      "id": "room|0",
      "roomType": "Bedroom",
      "children": [],
      "ceilings": [],
      "floorMaterial": {
        "name": "WoodFloorsCross"
      },
      "floorPolygon": [
        {
          "x": -0.5,
          "y": 0,
          "z": -0.5
        },
        {
          "x": -0.5,
          "y": 0,
          "z": 3.062241941690445
        },
        {
          "x": 4.425704598426819,
          "y": 0,
          "z": 3.062241941690445
        },
        {
          "x": 4.425704598426819,
          "y": 0,
          "z": -0.5
        }
      ]
    }
  ],
  "walls": [
    {
      "id": "wall|0|0.00|0.00|0.00|2.56",
      "roomId": "room|0",
      "color": {
        "r": 1.0,
        "g": 1.0,
        "b": 1.0
      },
      "material": {
        "name": "PureWhite",
        "color": {
          "r": 1.0,
          "g": 1.0,
          "b": 1.0
        }
      },
      "polygon": [
        {
          "x": 0.0,
          "y": 0,
          "z": 0.0
        },
        {
          "x": 0.0,
          "y": 0,
          "z": 2.562241941690445
        },
        {
          "x": 0.0,
          "y": 3,
          "z": 2.562241941690445
        },
        {
          "x": 0.0,
          "y": 3,
          "z": 0.0
        }
      ]
    },
    {
      "id": "wall|0|0.00|2.56|3.93|2.56",
      "roomId": "room|0",
      "color": {
        "r": 1.0,
        "g": 1.0,
        "b": 1.0
      },
      "material": {
        "name": "PureWhite",
        "color": {
          "r": 1.0,
          "g": 1.0,
          "b": 1.0
        }
      },
      "polygon": [
        {
          "x": 0.0,
          "y": 0,
          "z": 2.562241941690445
        },
        {
          "x": 3.925704598426819,
          "y": 0,
          "z": 2.562241941690445
        },
        {
          "x": 3.925704598426819,
          "y": 3,
          "z": 2.562241941690445
        },
        {
          "x": 0.0,
          "y": 3,
          "z": 2.562241941690445
        }
      ]
    },
    {
      "id": "wall|0|3.93|2.56|3.93|0.00",
      "roomId": "room|0",
      "color": {
        "r": 1.0,
        "g": 1.0,
        "b": 1.0
      },
      "material": {
        "name": "PureWhite",
        "color": {
          "r": 1.0,
          "g": 1.0,
          "b": 1.0
        }
      },
      "polygon": [
        {
          "x": 3.925704598426819,
          "y": 0,
          "z": 2.562241941690445
        },
        {
          "x": 3.925704598426819,
          "y": 0,
          "z": 0.0
        },
        {
          "x": 3.925704598426819,
          "y": 3,
          "z": 0.0
        },
        {
          "x": 3.925704598426819,
          "y": 3,
          "z": 2.562241941690445
        }
      ]
    },
    {
      "id": "wall|0|3.93|0.00|0.00|0.00",
      "roomId": "room|0",
      "color": {
        "r": 1.0,
        "g": 1.0,
        "b": 1.0
      },
      "material": {
        "name": "PureWhite",
        "color": {
          "r": 1.0,
          "g": 1.0,
          "b": 1.0
        }
      },
      "polygon": [
        {
          "x": 3.925704598426819,
          "y": 0,
          "z": 0.0
        },
        {
          "x": 0.0,
          "y": 0,
          "z": 0.0
        },
        {
          "x": 0.0,
          "y": 3,
          "z": 0.0
        },
        {
          "x": 3.925704598426819,
          "y": 3,
          "z": 0.0
        }
      ]
    },
    {
      "id": "furn|0|0",
      "roomId": "room|0",
      "material": {
        "name": "PureWhite"
      },
      "polygon": [
        {
          "x": 2.4103683201425885,
          "y": 0.0,
          "z": 2.555856441860721
        },
        {
          "x": 2.3986177411037866,
          "y": 0.0,
          "z": 0.9840127506085941
        },
        {
          "x": 2.3986177411037866,
          "y": 3.0,
          "z": 0.9840127506085941
        },
        {
          "x": 2.4103683201425885,
          "y": 3.0,
          "z": 2.555856441860721
        }
      ]
    },
    {
      "id": "furn|0|1",
      "roomId": "room|0",
      "material": {
        "name": "PureWhite"
      },
      "polygon": [
        {
          "x": 2.3986177411037866,
          "y": 0.0,
          "z": 0.9840127506085941
        },
        {
          "x": 0.6961503060704852,
          "y": 0.0,
          "z": 0.9967398291773348
        },
        {
          "x": 0.6961503060704852,
          "y": 3.0,
          "z": 0.9967398291773348
        },
        {
          "x": 2.3986177411037866,
          "y": 3.0,
          "z": 0.9840127506085941
        }
      ]
    },
    {
      "id": "furn|0|2",
      "roomId": "room|0",
      "material": {
        "name": "PureWhite"
      },
      "polygon": [
        {
          "x": 0.6961503060704852,
          "y": 0.0,
          "z": 0.9967398291773348
        },
        {
          "x": 0.7079008851092874,
          "y": 0.0,
          "z": 2.5685835204294616
        },
        {
          "x": 0.7079008851092874,
          "y": 3.0,
          "z": 2.5685835204294616
        },
        {
          "x": 0.6961503060704852,
          "y": 3.0,
          "z": 0.9967398291773348
        }
      ]
    },
    {
      "id": "furn|0|3",
      "roomId": "room|0",
      "material": {
        "name": "PureWhite"
      },
      "polygon": [
        {
          "x": 0.7079008851092874,
          "y": 0.0,
          "z": 2.5685835204294616
        },
        {
          "x": 2.4103683201425885,
          "y": 0.0,
          "z": 2.555856441860721
        },
        {
          "x": 2.4103683201425885,
          "y": 3.0,
          "z": 2.555856441860721
        },
        {
          "x": 0.7079008851092874,
          "y": 3.0,
          "z": 2.5685835204294616
        }
      ]
    },
    {
      "id": "furn|0|lid",
      "roomId": "room|0",
      "material": {
        "name": "PureWhite"
      },
      "polygon": [
        {
          "x": 2.4103683201425885,
          "y": 3.0,
          "z": 2.555856441860721
        },
        {
          "x": 0.7079008851092874,
          "y": 3.0,
          "z": 2.5685835204294616
        },
        {
          "x": 0.6961503060704852,
          "y": 3.0,
          "z": 0.9967398291773348
        },
        {
          "x": 2.3986177411037866,
          "y": 3.0,
          "z": 0.9840127506085941
        }
      ]
    },
    {
      "id": "furn|1|0",
      "roomId": "room|0",
      "material": {
        "name": "PureWhite"
      },
      "polygon": [
        {
          "x": 0.2564398168425061,
          "y": 0.0,
          "z": 0.6919186446027519
        },
        {
          "x": 0.25656807874484117,
          "y": 0.0,
          "z": 1.2105955057658087
        },
        {
          "x": 0.25656807874484117,
          "y": 3.0,
          "z": 1.2105955057658087
        },
        {
          "x": 0.2564398168425061,
          "y": 3.0,
          "z": 0.6919186446027519
        }
      ]
    },
    {
      "id": "furn|1|1",
      "roomId": "room|0",
      "material": {
        "name": "PureWhite"
      },
      "polygon": [
        {
          "x": 0.25656807874484117,
          "y": 0.0,
          "z": 1.2105955057658087
        },
        {
          "x": 0.7906629921098254,
          "y": 0.0,
          "z": 1.2104634311838387
        },
        {
          "x": 0.7906629921098254,
          "y": 3.0,
          "z": 1.2104634311838387
        },
        {
          "x": 0.25656807874484117,
          "y": 3.0,
          "z": 1.2105955057658087
        }
      ]
    },
    {
      "id": "furn|1|2",
      "roomId": "room|0",
      "material": {
        "name": "PureWhite"
      },
      "polygon": [
        {
          "x": 0.7906629921098254,
          "y": 0.0,
          "z": 1.2104634311838387
        },
        {
          "x": 0.7905347302074903,
          "y": 0.0,
          "z": 0.6917865700207819
        },
        {
          "x": 0.7905347302074903,
          "y": 3.0,
          "z": 0.6917865700207819
        },
        {
          "x": 0.7906629921098254,
          "y": 3.0,
          "z": 1.2104634311838387
        }
      ]
    },
    {
      "id": "furn|1|3",
      "roomId": "room|0",
      "material": {
        "name": "PureWhite"
      },
      "polygon": [
        {
          "x": 0.7905347302074903,
          "y": 0.0,
          "z": 0.6917865700207819
        },
        {
          "x": 0.2564398168425061,
          "y": 0.0,
          "z": 0.6919186446027519
        },
        {
          "x": 0.2564398168425061,
          "y": 3.0,
          "z": 0.6919186446027519
        },
        {
          "x": 0.7905347302074903,
          "y": 3.0,
          "z": 0.6917865700207819
        }
      ]
    },
    {
      "id": "furn|1|lid",
      "roomId": "room|0",
      "material": {
        "name": "PureWhite"
      },
      "polygon": [
        {
          "x": 0.2564398168425061,
          "y": 3.0,
          "z": 0.6919186446027519
        },
        {
          "x": 0.7905347302074903,
          "y": 3.0,
          "z": 0.6917865700207819
        },
        {
          "x": 0.7906629921098254,
          "y": 3.0,
          "z": 1.2104634311838387
        },
        {
          "x": 0.25656807874484117,
          "y": 3.0,
          "z": 1.2105955057658087
        }
      ]
    },
    {
      "id": "furn|2|0",
      "roomId": "room|0",
      "material": {
        "name": "PureWhite"
      },
      "polygon": [
        {
          "x": 2.5685469663501235,
          "y": 0.0,
          "z": 1.5171832695537844
        },
        {
          "x": 2.5675876838159932,
          "y": 0.0,
          "z": 1.9977813877378972
        },
        {
          "x": 2.5675876838159932,
          "y": 3.0,
          "z": 1.9977813877378972
        },
        {
          "x": 2.5685469663501235,
          "y": 3.0,
          "z": 1.5171832695537844
        }
      ]
    },
    {
      "id": "furn|2|1",
      "roomId": "room|0",
      "material": {
        "name": "PureWhite"
      },
      "polygon": [
        {
          "x": 2.5675876838159932,
          "y": 0.0,
          "z": 1.9977813877378972
        },
        {
          "x": 3.0891448700069932,
          "y": 0.0,
          "z": 1.998822425312396
        },
        {
          "x": 3.0891448700069932,
          "y": 3.0,
          "z": 1.998822425312396
        },
        {
          "x": 2.5675876838159932,
          "y": 3.0,
          "z": 1.9977813877378972
        }
      ]
    },
    {
      "id": "furn|2|2",
      "roomId": "room|0",
      "material": {
        "name": "PureWhite"
      },
      "polygon": [
        {
          "x": 3.0891448700069932,
          "y": 0.0,
          "z": 1.998822425312396
        },
        {
          "x": 3.0901041525411235,
          "y": 0.0,
          "z": 1.5182243071282833
        },
        {
          "x": 3.0901041525411235,
          "y": 3.0,
          "z": 1.5182243071282833
        },
        {
          "x": 3.0891448700069932,
          "y": 3.0,
          "z": 1.998822425312396
        }
      ]
    },
    {
      "id": "furn|2|3",
      "roomId": "room|0",
      "material": {
        "name": "PureWhite"
      },
      "polygon": [
        {
          "x": 3.0901041525411235,
          "y": 0.0,
          "z": 1.5182243071282833
        },
        {
          "x": 2.5685469663501235,
          "y": 0.0,
          "z": 1.5171832695537844
        },
        {
          "x": 2.5685469663501235,
          "y": 3.0,
          "z": 1.5171832695537844
        },
        {
          "x": 3.0901041525411235,
          "y": 3.0,
          "z": 1.5182243071282833
        }
      ]
    },
    {
      "id": "furn|2|lid",
      "roomId": "room|0",
      "material": {
        "name": "PureWhite"
      },
      "polygon": [
        {
          "x": 2.5685469663501235,
          "y": 3.0,
          "z": 1.5171832695537844
        },
        {
          "x": 3.0901041525411235,
          "y": 3.0,
          "z": 1.5182243071282833
        },
        {
          "x": 3.0891448700069932,
          "y": 3.0,
          "z": 1.998822425312396
        },
        {
          "x": 2.5675876838159932,
          "y": 3.0,
          "z": 1.9977813877378972
        }
      ]
    },
    {
      "id": "furn|3|0",
      "roomId": "room|0",
      "material": {
        "name": "PureWhite"
      },
      "polygon": [
        {
          "x": 0.8852536393037134,
          "y": 0.0,
          "z": -0.42799547937472765
        },
        {
          "x": 0.4280381518779173,
          "y": 0.0,
          "z": -0.428017519110974
        },
        {
          "x": 0.4280381518779173,
          "y": 3.0,
          "z": -0.428017519110974
        },
        {
          "x": 0.8852536393037134,
          "y": 3.0,
          "z": -0.42799547937472765
        }
      ]
    },
    {
      "id": "furn|3|1",
      "roomId": "room|0",
      "material": {
        "name": "PureWhite"
      },
      "polygon": [
        {
          "x": 0.4280381518779173,
          "y": 0.0,
          "z": -0.428017519110974
        },
        {
          "x": 0.42797484866473146,
          "y": 0.0,
          "z": 0.8852109673317284
        },
        {
          "x": 0.42797484866473146,
          "y": 3.0,
          "z": 0.8852109673317284
        },
        {
          "x": 0.4280381518779173,
          "y": 3.0,
          "z": -0.428017519110974
        }
      ]
    },
    {
      "id": "furn|3|2",
      "roomId": "room|0",
      "material": {
        "name": "PureWhite"
      },
      "polygon": [
        {
          "x": 0.42797484866473146,
          "y": 0.0,
          "z": 0.8852109673317284
        },
        {
          "x": 0.8851903360905276,
          "y": 0.0,
          "z": 0.8852330070679747
        },
        {
          "x": 0.8851903360905276,
          "y": 3.0,
          "z": 0.8852330070679747
        },
        {
          "x": 0.42797484866473146,
          "y": 3.0,
          "z": 0.8852109673317284
        }
      ]
    },
    {
      "id": "furn|3|3",
      "roomId": "room|0",
      "material": {
        "name": "PureWhite"
      },
      "polygon": [
        {
          "x": 0.8851903360905276,
          "y": 0.0,
          "z": 0.8852330070679747
        },
        {
          "x": 0.8852536393037134,
          "y": 0.0,
          "z": -0.42799547937472765
        },
        {
          "x": 0.8852536393037134,
          "y": 3.0,
          "z": -0.42799547937472765
        },
        {
          "x": 0.8851903360905276,
          "y": 3.0,
          "z": 0.8852330070679747
        }
      ]
    },
    {
      "id": "furn|3|lid",
      "roomId": "room|0",
      "material": {
        "name": "PureWhite"
      },
      "polygon": [
        {
          "x": 0.8852536393037134,
          "y": 3.0,
          "z": -0.42799547937472765
        },
        {
          "x": 0.8851903360905276,
          "y": 3.0,
          "z": 0.8852330070679747
        },
        {
          "x": 0.42797484866473146,
          "y": 3.0,
          "z": 0.8852109673317284
        },
        {
          "x": 0.4280381518779173,
          "y": 3.0,
          "z": -0.428017519110974
        }
      ]
    },
    {
      "id": "furn|4|0",
      "roomId": "room|0",
      "material": {
        "name": "PureWhite"
      },
      "polygon": [
        {
          "x": 3.13062442160561,
          "y": 0.0,
          "z": 2.1727464304987962
        },
        {
          "x": 3.6047405357117164,
          "y": 0.0,
          "z": 2.1730418913806946
        },
        {
          "x": 3.6047405357117164,
          "y": 3.0,
          "z": 2.1730418913806946
        },
        {
          "x": 3.13062442160561,
          "y": 3.0,
          "z": 2.1727464304987962
        }
      ]
    },
    {
      "id": "furn|4|1",
      "roomId": "room|0",
      "material": {
        "name": "PureWhite"
      },
      "polygon": [
        {
          "x": 3.6047405357117164,
          "y": 0.0,
          "z": 2.1730418913806946
        },
        {
          "x": 3.6054356017021902,
          "y": 0.0,
          "z": 1.0576929344113293
        },
        {
          "x": 3.6054356017021902,
          "y": 3.0,
          "z": 1.0576929344113293
        },
        {
          "x": 3.6047405357117164,
          "y": 3.0,
          "z": 2.1730418913806946
        }
      ]
    },
    {
      "id": "furn|4|2",
      "roomId": "room|0",
      "material": {
        "name": "PureWhite"
      },
      "polygon": [
        {
          "x": 3.6054356017021902,
          "y": 0.0,
          "z": 1.0576929344113293
        },
        {
          "x": 3.131319487596084,
          "y": 0.0,
          "z": 1.057397473529431
        },
        {
          "x": 3.131319487596084,
          "y": 3.0,
          "z": 1.057397473529431
        },
        {
          "x": 3.6054356017021902,
          "y": 3.0,
          "z": 1.0576929344113293
        }
      ]
    },
    {
      "id": "furn|4|3",
      "roomId": "room|0",
      "material": {
        "name": "PureWhite"
      },
      "polygon": [
        {
          "x": 3.131319487596084,
          "y": 0.0,
          "z": 1.057397473529431
        },
        {
          "x": 3.13062442160561,
          "y": 0.0,
          "z": 2.1727464304987962
        },
        {
          "x": 3.13062442160561,
          "y": 3.0,
          "z": 2.1727464304987962
        },
        {
          "x": 3.131319487596084,
          "y": 3.0,
          "z": 1.057397473529431
        }
      ]
    },
    {
      "id": "furn|4|lid",
      "roomId": "room|0",
      "material": {
        "name": "PureWhite"
      },
      "polygon": [
        {
          "x": 3.13062442160561,
          "y": 3.0,
          "z": 2.1727464304987962
        },
        {
          "x": 3.131319487596084,
          "y": 3.0,
          "z": 1.057397473529431
        },
        {
          "x": 3.6054356017021902,
          "y": 3.0,
          "z": 1.0576929344113293
        },
        {
          "x": 3.6047405357117164,
          "y": 3.0,
          "z": 2.1730418913806946
        }
      ]
    }
  ],
  "windows": [],
  "furniture_boxes": [
    [
      0.6961503060704852,
      2.4103683201425885,
      0.9840127506085941,
      2.5685835204294616
    ],
    [
      0.2564398168425061,
      0.7906629921098254,
      0.6917865700207819,
      1.2105955057658087
    ],
    [
      2.5675876838159932,
      3.0901041525411235,
      1.5171832695537844,
      1.998822425312396
    ],
    [
      0.42797484866473146,
      0.8852536393037134,
      -0.428017519110974,
      0.8852330070679747
    ],
    [
      3.13062442160561,
      3.6054356017021902,
      1.057397473529431,
      2.1730418913806946
    ]
  ],
  "room_dims": {
    "l": 3.925704598426819,
    "w": 2.562241941690445
  },
  "objects_raw": [
    {
      "class": "bed",
      "size": {
        "x": 1.7025150060653687,
        "y": 0.8935767412185669,
        "z": 1.5718876123428345
      },
      "position": {
        "x": -0.35899782180786133,
        "y": 0.0049666897393763065,
        "z": 0.466280460357666
      },
      "rotation": {
        "x": 0,
        "y": 3.1341171264648438,
        "z": 0
      }
    },
    {
      "class": "nightstand",
      "size": {
        "x": 0.5340949296951294,
        "y": 0.5619486570358276,
        "z": 0.5186768770217896
      },
      "position": {
        "x": -1.3887057304382324,
        "y": -7.68117606639862e-05,
        "z": -0.3588266372680664
      },
      "rotation": {
        "x": 0,
        "y": -0.00024728671996854246,
        "z": 0
      }
    },
    {
      "class": "nightstand",
      "size": {
        "x": 0.5215582251548767,
        "y": 0.5109233856201172,
        "z": 0.4805990755558014
      },
      "position": {
        "x": 0.9165887832641602,
        "y": 0.004066391382366419,
        "z": 0.4479851722717285
      },
      "rotation": {
        "x": 0,
        "y": 0.0019960154313594103,
        "z": 0
      }
    },
    {
      "class": "wardrobe",
      "size": {
        "x": 1.3132284879684448,
        "y": 2.2081427574157715,
        "z": 0.45721548795700073
      },
      "position": {
        "x": -1.2556428909301758,
        "y": 0.03851613774895668,
        "z": -1.0814099311828613
      },
      "rotation": {
        "x": 0,
        "y": 1.5708445310592651,
        "z": 0
      }
    },
    {
      "class": "desk",
      "size": {
        "x": 1.1153491735458374,
        "y": 1.1136393547058105,
        "z": 0.4741162061691284
      },
      "position": {
        "x": 1.455772876739502,
        "y": 0.002788442187011242,
        "z": 0.30520200729370117
      },
      "rotation": {
        "x": 0,
        "y": -1.5701731443405151,
        "z": 0
      }
    }
  ]
}