{
  "metadata": {
    "schema": "1.0.0",
    "agent": {
      "horizon": 30,
      "position": {
        "x": 0.25,
        "y": 0.95,
        "z": 0.25
      },
      "rotation": {
        "x": 0,
        "y": 0,
        "z": 0
      },
      "standing": true
    },
    "agentPoses": {
      "default": {
        "horizon": 30,
        "position": {
          "x": 0.25,
          "y": 0.95,
          "z": 0.25
        },
        "rotation": {
          "x": 0,
          "y": 0,
          "z": 0
        },
        "standing": true
      },
      "arm": {
        "horizon": 30,
        "position": {
          "x": 0.25,
          "y": 0.95,
          "z": 0.25
        },
        "rotation": {
          "x": 0,
          "y": 0,
          "z": 0
        },
        "standing": true
      },
      "locobot": {
        "horizon": 30,
        "position": {
          "x": 0.25,
          "y": 0.95,
          "z": 0.25
        },
        "rotation": {
          "x": 0,
          "y": 0,
          "z": 0
        },
        "standing": null
      },
      "stretch": {
        "horizon": 30,
        "position": {
          "x": 0.25,
          "y": 0.95,
          "z": 0.25
        },
        "rotation": {
          "x": 0,
          "y": 0,
          "z": 0
        },
        "standing": true
      }
    }
  },
  "proceduralParameters": {
    "floorColliderThickness": 1.0,
    "receptacleHeight": 0.7,
    "skyboxId": "Sky1",
    "ceilingMaterial": {
      "name": "PureWhite"
    },
    "lights": [
      {
        "id": "DirectionalLight",
        "type": "directional",
        "intensity": 1.0,
        "indirectMultiplier": 1.0,
        "position": {
          "x": 0.84,
          "y": 0.1855,
          "z": -1.09
        },
        "rotation": {
          "x": 66,
          "y": 75,
          "z": 0
        },
        "rgb": {
          "r": 1.0,
          "g": 1.0,
          "b": 1.0
        },
        "shadow": {
          "type": "Soft",
          "strength": 1,
          "normalBias": 0,
          "bias": 0,
          "nearPlane": 0.2,
          "resolution": "FromQualitySettings"
        }
      }
    ]
  },
  "rooms": [
    {
      "id": "room|0",
      "roomType": "Bedroom",
      "children": [],
      "ceilings": [],
      "floorMaterial": {
        "name": "WoodFloorsCross"
      },
      "floorPolygon": [
        {
          "x": -0.5,
          "y": 0,
          "z": -0.5
        },
        {
          "x": -0.5,
          "y": 0,
          "z": 6.51467490196228
        },
        {
          "x": 6.802033722400665,
          "y": 0,
          "z": 6.51467490196228
        },
        {
          "x": 6.802033722400665,
          "y": 0,
          "z": -0.5
        }
      ]
    }
  ],
  "walls": [
    {
      "id": "wall|0|0.00|0.00|0.00|6.01",
      "roomId": "room|0",
      "color": {
        "r": 1.0,
        "g": 1.0,
        "b": 1.0
      },
      "material": {
        "name": "PureWhite",
        "color": {
          "r": 1.0,
          "g": 1.0,
          "b": 1.0
        }
      },
      "polygon": [
        {
          "x": 0.0,
          "y": 0,
          "z": 0.0
        },
        {
          "x": 0.0,
          "y": 0,
          "z": 6.01467490196228
        },
        {
          "x": 0.0,
          "y": 3,
          "z": 6.01467490196228
        },
        {
          "x": 0.0,
          "y": 3,
          "z": 0.0
        }
      ]
    },
    {
      "id": "wall|0|0.00|6.01|6.30|6.01",
      "roomId": "room|0",
      "color": {
        "r": 1.0,
        "g": 1.0,
        "b": 1.0
      },
      "material": {
        "name": "PureWhite",
        "color": {
          "r": 1.0,
          "g": 1.0,
          "b": 1.0
        }
      },
      "polygon": [
        {
          "x": 0.0,
          "y": 0,
          "z": 6.01467490196228
        },
        {
          "x": 6.302033722400665,
          "y": 0,
          "z": 6.01467490196228
        },
        {
          "x": 6.302033722400665,
          "y": 3,
          "z": 6.01467490196228
        },
        {
          "x": 0.0,
          "y": 3,
          "z": 6.01467490196228
        }
      ]
    },
    {
      "id": "wall|0|6.30|6.01|6.30|0.00",
      "roomId": "room|0",
      "color": {
        "r": 1.0,
        "g": 1.0,
        "b": 1.0
      },
      "material": {
        "name": "PureWhite",
        "color": {
          "r": 1.0,
          "g": 1.0,
          "b": 1.0
        }
      },
      "polygon": [
        {
          "x": 6.302033722400665,
          "y": 0,
          "z": 6.01467490196228
        },
        {
          "x": 6.302033722400665,
          "y": 0,
          "z": 0.0
        },
        {
          "x": 6.302033722400665,
          "y": 3,
          "z": 0.0
        },
        {
          "x": 6.302033722400665,
          "y": 3,
          "z": 6.01467490196228
        }
      ]
    },
    {
      "id": "wall|0|6.30|0.00|0.00|0.00",
      "roomId": "room|0",
      "color": {
        "r": 1.0,
        "g": 1.0,
        "b": 1.0
      },
      "material": {
        "name": "PureWhite",
        "color": {
          "r": 1.0,
          "g": 1.0,
          "b": 1.0
        }
      },
      "polygon": [
        {
          "x": 6.302033722400665,
          "y": 0,
          "z": 0.0
        },
        {
          "x": 0.0,
          "y": 0,
          "z": 0.0
        },
        {
          "x": 0.0,
          "y": 3,
          "z": 0.0
        },
        {
          "x": 6.302033722400665,
          "y": 3,
          "z": 0.0
        }
      ]
    },
    {
      "id": "furn|0|0",
      "roomId": "room|0",
      "material": {
        "name": "PureWhite"
      },
      "polygon": [
        {
          "x": 1.976745328805229,
          "y": 0.0,
          "z": 2.4106369941072945
        },
        {
          "x": 0.03297425134220522,
          "y": 0.0,
          "z": 2.4102121744972624
        },
        {
          "x": 0.03297425134220522,
          "y": 3.0,
          "z": 2.4102121744972624
        },
        {
          "x": 1.976745328805229,
          "y": 3.0,
          "z": 2.4106369941072945
        }
      ]
    },
    {
      "id": "furn|0|1",
      "roomId": "room|0",
      "material": {
        "name": "PureWhite"
      },
      "polygon": [
        {
          "x": 0.03297425134220522,
          "y": 0.0,
          "z": 2.4102121744972624
        },
        {
          "x": 0.03253511438629941,
          "y": 0.0,
          "z": 4.419492569701147
        },
        {
          "x": 0.03253511438629941,
          "y": 3.0,
          "z": 4.419492569701147
        },
        {
          "x": 0.03297425134220522,
          "y": 3.0,
          "z": 2.4102121744972624
        }
      ]
    },
    {
      "id": "furn|0|2",
      "roomId": "room|0",
      "material": {
        "name": "PureWhite"
      },
      "polygon": [
        {
          "x": 0.03253511438629941,
          "y": 0.0,
          "z": 4.419492569701147
        },
        {
          "x": 1.9763061918493232,
          "y": 0.0,
          "z": 4.419917389311179
        },
        {
          "x": 1.9763061918493232,
          "y": 3.0,
          "z": 4.419917389311179
        },
        {
          "x": 0.03253511438629941,
          "y": 3.0,
          "z": 4.419492569701147
        }
      ]
    },
    {
      "id": "furn|0|3",
      "roomId": "room|0",
      "material": {
        "name": "PureWhite"
      },
      "polygon": [
        {
          "x": 1.9763061918493232,
          "y": 0.0,
          "z": 4.419917389311179
        },
        {
          "x": 1.976745328805229,
          "y": 0.0,
          "z": 2.4106369941072945
        },
        {
          "x": 1.976745328805229,
          "y": 3.0,
          "z": 2.4106369941072945
        },
        {
          "x": 1.9763061918493232,
          "y": 3.0,
          "z": 4.419917389311179
        }
      ]
    },
    {
      "id": "furn|0|lid",
      "roomId": "room|0",
      "material": {
        "name": "PureWhite"
      },
      "polygon": [
        {
          "x": 1.976745328805229,
          "y": 3.0,
          "z": 2.4106369941072945
        },
        {
          "x": 1.9763061918493232,
          "y": 3.0,
          "z": 4.419917389311179
        },
        {
          "x": 0.03253511438629941,
          "y": 3.0,
          "z": 4.419492569701147
        },
        {
          "x": 0.03297425134220522,
          "y": 3.0,
          "z": 2.4102121744972624
        }
      ]
    },
    {
      "id": "furn|1|0",
      "roomId": "room|0",
      "material": {
        "name": "PureWhite"
      },
      "polygon": [
        {
          "x": 1.980911720624425,
          "y": 0.0,
          "z": 1.9271289577637858
        },
        {
          "x": 1.5398641027457909,
          "y": 0.0,
          "z": 1.9275159576839198
        },
        {
          "x": 1.5398641027457909,
          "y": 3.0,
          "z": 1.9275159576839198
        },
        {
          "x": 1.980911720624425,
          "y": 3.0,
          "z": 1.9271289577637858
        }
      ]
    },
    {
      "id": "furn|1|1",
      "roomId": "room|0",
      "material": {
        "name": "PureWhite"
      },
      "polygon": [
        {
          "x": 1.5398641027457909,
          "y": 0.0,
          "z": 1.9275159576839198
        },
        {
          "x": 1.540251266130946,
          "y": 0.0,
          "z": 2.368749869808083
        },
        {
          "x": 1.540251266130946,
          "y": 3.0,
          "z": 2.368749869808083
        },
        {
          "x": 1.5398641027457909,
          "y": 3.0,
          "z": 1.9275159576839198
        }
      ]
    },
    {
      "id": "furn|1|2",
      "roomId": "room|0",
      "material": {
        "name": "PureWhite"
      },
      "polygon": [
        {
          "x": 1.540251266130946,
          "y": 0.0,
          "z": 2.368749869808083
        },
        {
          "x": 1.9812988840095802,
          "y": 0.0,
          "z": 2.368362869887949
        },
        {
          "x": 1.9812988840095802,
          "y": 3.0,
          "z": 2.368362869887949
        },
        {
          "x": 1.540251266130946,
          "y": 3.0,
          "z": 2.368749869808083
        }
      ]
    },
    {
      "id": "furn|1|3",
      "roomId": "room|0",
      "material": {
        "name": "PureWhite"
      },
      "polygon": [
        {
          "x": 1.9812988840095802,
          "y": 0.0,
          "z": 2.368362869887949
        },
        {
          "x": 1.980911720624425,
          "y": 0.0,
          "z": 1.9271289577637858
        },
        {
          "x": 1.980911720624425,
          "y": 3.0,
          "z": 1.9271289577637858
        },
        {
          "x": 1.9812988840095802,
          "y": 3.0,
          "z": 2.368362869887949
        }
      ]
    },
    {
      "id": "furn|1|lid",
      "roomId": "room|0",
      "material": {
        "name": "PureWhite"
      },
      "polygon": [
        {
          "x": 1.980911720624425,
          "y": 3.0,
          "z": 1.9271289577637858
        },
        {
          "x": 1.9812988840095802,
          "y": 3.0,
          "z": 2.368362869887949
        },
        {
          "x": 1.540251266130946,
          "y": 3.0,
          "z": 2.368749869808083
        },
        {
          "x": 1.5398641027457909,
          "y": 3.0,
          "z": 1.9275159576839198
        }
      ]
    },
    {
      "id": "furn|2|0",
      "roomId": "room|0",
      "material": {
        "name": "PureWhite"
      },
      "polygon": [
        {
          "x": 1.982024794936299,
          "y": 0.0,
          "z": 4.633562433387109
        },
        {
          "x": 1.5317239734043047,
          "y": 0.0,
          "z": 4.63334855240433
        },
        {
          "x": 1.5317239734043047,
          "y": 3.0,
          "z": 4.63334855240433
        },
        {
          "x": 1.982024794936299,
          "y": 3.0,
          "z": 4.633562433387109
        }
      ]
    },
    {
      "id": "furn|2|1",
      "roomId": "room|0",
      "material": {
        "name": "PureWhite"
      },
      "polygon": [
        {
          "x": 1.5317239734043047,
          "y": 0.0,
          "z": 4.63334855240433
        },
        {
          "x": 1.5315328775643113,
          "y": 0.0,
          "z": 5.035677981709174
        },
        {
          "x": 1.5315328775643113,
          "y": 3.0,
          "z": 5.035677981709174
        },
        {
          "x": 1.5317239734043047,
          "y": 3.0,
          "z": 4.63334855240433
        }
      ]
    },
    {
      "id": "furn|2|2",
      "roomId": "room|0",
      "material": {
        "name": "PureWhite"
      },
      "polygon": [
        {
          "x": 1.5315328775643113,
          "y": 0.0,
          "z": 5.035677981709174
        },
        {
          "x": 1.9818336990963057,
          "y": 0.0,
          "z": 5.035891862691953
        },
        {
          "x": 1.9818336990963057,
          "y": 3.0,
          "z": 5.035891862691953
        },
        {
          "x": 1.5315328775643113,
          "y": 3.0,
          "z": 5.035677981709174
        }
      ]
    },
    {
      "id": "furn|2|3",
      "roomId": "room|0",
      "material": {
        "name": "PureWhite"
      },
      "polygon": [
        {
          "x": 1.9818336990963057,
          "y": 0.0,
          "z": 5.035891862691953
        },
        {
          "x": 1.982024794936299,
          "y": 0.0,
          "z": 4.633562433387109
        },
        {
          "x": 1.982024794936299,
          "y": 3.0,
          "z": 4.633562433387109
        },
        {
          "x": 1.9818336990963057,
          "y": 3.0,
          "z": 5.035891862691953
        }
      ]
    },
    {
      "id": "furn|2|lid",
      "roomId": "room|0",
      "material": {
        "name": "PureWhite"
      },
      "polygon": [
        {
          "x": 1.982024794936299,
          "y": 3.0,
          "z": 4.633562433387109
        },
        {
          "x": 1.9818336990963057,
          "y": 3.0,
          "z": 5.035891862691953
        },
        {
          "x": 1.5315328775643113,
          "y": 3.0,
          "z": 5.035677981709174
        },
        {
          "x": 1.5317239734043047,
          "y": 3.0,
          "z": 4.63334855240433
        }
      ]
    },
    {
      "id": "furn|3|0",
      "roomId": "room|0",
      "material": {
        "name": "PureWhite"
      },
      "polygon": [
        {
          "x": 1.6559766274730507,
          "y": 0.0,
          "z": -0.002720620763808801
        },
        {
          "x": 1.65462840827932,
          "y": 0.0,
          "z": 0.5580324748725294
        },
        {
          "x": 1.65462840827932,
          "y": 3.0,
          "z": 0.5580324748725294
        },
        {
          "x": 1.6559766274730507,
          "y": 3.0,
          "z": -0.002720620763808801
        }
      ]
    },
    {
      "id": "furn|3|1",
      "roomId": "room|0",
      "material": {
        "name": "PureWhite"
      },
      "polygon": [
        {
          "x": 1.65462840827932,
          "y": 0.0,
          "z": 0.5580324748725294
        },
        {
          "x": 3.918430830832308,
          "y": 0.0,
          "z": 0.5634753371601406
        },
        {
          "x": 3.918430830832308,
          "y": 3.0,
          "z": 0.5634753371601406
        },
        {
          "x": 1.65462840827932,
          "y": 3.0,
          "z": 0.5580324748725294
        }
      ]
    },
    {
      "id": "furn|3|2",
      "roomId": "room|0",
      "material": {
        "name": "PureWhite"
      },
      "polygon": [
        {
          "x": 3.918430830832308,
          "y": 0.0,
          "z": 0.5634753371601406
        },
        {
          "x": 3.919779050026039,
          "y": 0.0,
          "z": 0.00272224152380246
        },
        {
          "x": 3.919779050026039,
          "y": 3.0,
          "z": 0.00272224152380246
        },
        {
          "x": 3.918430830832308,
          "y": 3.0,
          "z": 0.5634753371601406
        }
      ]
    },
    {
      "id": "furn|3|3",
      "roomId": "room|0",
      "material": {
        "name": "PureWhite"
      },
      "polygon": [
        {
          "x": 3.919779050026039,
          "y": 0.0,
          "z": 0.00272224152380246
        },
        {
          "x": 1.6559766274730507,
          "y": 0.0,
          "z": -0.002720620763808801
        },
        {
          "x": 1.6559766274730507,
          "y": 3.0,
          "z": -0.002720620763808801
        },
        {
          "x": 3.919779050026039,
          "y": 3.0,
          "z": 0.00272224152380246
        }
      ]
    },
    {
      "id": "furn|3|lid",
      "roomId": "room|0",
      "material": {
        "name": "PureWhite"
      },
      "polygon": [
        {
          "x": 1.6559766274730507,
          "y": 3.0,
          "z": -0.002720620763808801
        },
        {
          "x": 3.919779050026039,
          "y": 3.0,
          "z": 0.00272224152380246
        },
        {
          "x": 3.918430830832308,
          "y": 3.0,
          "z": 0.5634753371601406
        },
        {
          "x": 1.65462840827932,
          "y": 3.0,
          "z": 0.5580324748725294
        }
      ]
    },
    {
      "id": "furn|4|0",
      "roomId": "room|0",
      "material": {
        "name": "PureWhite"
      },
      "polygon": [
        {
          "x": 5.393384663714275,
          "y": 0.0,
          "z": 4.420825341549851
        },
        {
          "x": 5.747523797888262,
          "y": 0.0,
          "z": 4.418553531214267
        },
        {
          "x": 5.747523797888262,
          "y": 3.0,
          "z": 4.418553531214267
        },
        {
          "x": 5.393384663714275,
          "y": 3.0,
          "z": 4.420825341549851
        }
      ]
    },
    {
      "id": "furn|4|1",
      "roomId": "room|0",
      "material": {
        "name": "PureWhite"
      },
      "polygon": [
        {
          "x": 5.747523797888262,
          "y": 0.0,
          "z": 4.418553531214267
        },
        {
          "x": 5.738077195035115,
          "y": 0.0,
          "z": 2.9459782449331504
        },
        {
          "x": 5.738077195035115,
          "y": 3.0,
          "z": 2.9459782449331504
        },
        {
          "x": 5.747523797888262,
          "y": 3.0,
          "z": 4.418553531214267
        }
      ]
    },
    {
      "id": "furn|4|2",
      "roomId": "room|0",
      "material": {
        "name": "PureWhite"
      },
      "polygon": [
        {
          "x": 5.738077195035115,
          "y": 0.0,
          "z": 2.9459782449331504
        },
        {
          "x": 5.383938060861127,
          "y": 0.0,
          "z": 2.9482500552687343
        },
        {
          "x": 5.383938060861127,
          "y": 3.0,
          "z": 2.9482500552687343
        },
        {
          "x": 5.738077195035115,
          "y": 3.0,
          "z": 2.9459782449331504
        }
      ]
    },
    {
      "id": "furn|4|3",
      "roomId": "room|0",
      "material": {
        "name": "PureWhite"
      },
      "polygon": [
        {
          "x": 5.383938060861127,
          "y": 0.0,
          "z": 2.9482500552687343
        },
        {
          "x": 5.393384663714275,
          "y": 0.0,
          "z": 4.420825341549851
        },
        {
          "x": 5.393384663714275,
          "y": 3.0,
          "z": 4.420825341549851
        },
        {
          "x": 5.383938060861127,
          "y": 3.0,
          "z": 2.9482500552687343
        }
      ]
    },
    {
      "id": "furn|4|lid",
      "roomId": "room|0",
      "material": {
        "name": "PureWhite"
      },
      "polygon": [
        {
          "x": 5.393384663714275,
          "y": 3.0,
          "z": 4.420825341549851
        },
        {
          "x": 5.383938060861127,
          "y": 3.0,
          "z": 2.9482500552687343
        },
        {
          "x": 5.738077195035115,
          "y": 3.0,
          "z": 2.9459782449331504
        },
        {
          "x": 5.747523797888262,
          "y": 3.0,
          "z": 4.418553531214267
        }
      ]
    },
    {
      "id": "furn|5|0",
      "roomId": "room|0",
      "material": {
        "name": "PureWhite"
      },
      "polygon": [
        {
          "x": 3.388313692057825,
          "y": 1.3201359510421753,
          "z": 5.273025849458909
        },
        {
          "x": 3.3888188856438286,
          "y": 1.3201359510421753,
          "z": 6.014947638766817
        },
        {
          "x": 3.3888188856438286,
          "y": 3.0,
          "z": 6.014947638766817
        },
        {
          "x": 3.388313692057825,
          "y": 3.0,
          "z": 5.273025849458909
        }
      ]
    },
    {
      "id": "furn|5|1",
      "roomId": "room|0",
      "material": {
        "name": "PureWhite"
      },
      "polygon": [
        {
          "x": 3.3888188856438286,
          "y": 1.3201359510421753,
          "z": 6.014947638766817
        },
        {
          "x": 4.190148074185156,
          "y": 1.3201359510421753,
          "z": 6.014401993158126
        },
        {
          "x": 4.190148074185156,
          "y": 3.0,
          "z": 6.014401993158126
        },
        {
          "x": 3.3888188856438286,
          "y": 3.0,
          "z": 6.014947638766817
        }
      ]
    },
    {
      "id": "furn|5|2",
      "roomId": "room|0",
      "material": {
        "name": "PureWhite"
      },
      "polygon": [
        {
          "x": 4.190148074185156,
          "y": 1.3201359510421753,
          "z": 6.014401993158126
        },
        {
          "x": 4.189642880599153,
          "y": 1.3201359510421753,
          "z": 5.272480203850218
        },
        {
          "x": 4.189642880599153,
          "y": 3.0,
          "z": 5.272480203850218
        },
        {
          "x": 4.190148074185156,
          "y": 3.0,
          "z": 6.014401993158126
        }
      ]
    },
    {
      "id": "furn|5|3",
      "roomId": "room|0",
      "material": {
        "name": "PureWhite"
      },
      "polygon": [
        {
          "x": 4.189642880599153,
          "y": 1.3201359510421753,
          "z": 5.272480203850218
        },
        {
          "x": 3.388313692057825,
          "y": 1.3201359510421753,
          "z": 5.273025849458909
        },
        {
          "x": 3.388313692057825,
          "y": 3.0,
          "z": 5.273025849458909
        },
        {
          "x": 4.189642880599153,
          "y": 3.0,
          "z": 5.272480203850218
        }
      ]
    },
    {
      "id": "furn|5|lid",
      "roomId": "room|0",
      "material": {
        "name": "PureWhite"
      },
      "polygon": [
        {
          "x": 3.388313692057825,
          "y": 3.0,
          "z": 5.273025849458909
        },
        {
          "x": 4.189642880599153,
          "y": 3.0,
          "z": 5.272480203850218
        },
        {
          "x": 4.190148074185156,
          "y": 3.0,
          "z": 6.014401993158126
        },
        {
          "x": 3.3888188856438286,
          "y": 3.0,
          "z": 6.014947638766817
        }
      ]
    }
  ],
  "objects": [],
  "doors": [],
  "windows": [],
  "furniture_boxes": [
    [
      0.03253511438629941,
      1.976745328805229,
      2.4102121744972624,
      4.419917389311179
    ],
    [
      1.5398641027457909,
      1.9812988840095802,
      1.9271289577637858,
      2.368749869808083
    ],
    [
      1.5315328775643113,
      1.982024794936299,
      4.63334855240433,
      5.035891862691953
    ],
    [
      1.65462840827932,
      3.919779050026039,
      -0.002720620763808801,
      0.5634753371601406
    ],
    [
      5.383938060861127,
      5.747523797888262,
      2.9459782449331504,
      4.420825341549851
    ]
  ],
  "room_dims": {
    "l": 6.302033722400665,
    "w": 6.01467490196228
  },
  "objects_raw": [
    {
      "class": "bed",
      "size": {
        "x": 2.0092804431915283,
        "y": 0.6806248426437378,
        "z": 1.9437711238861084
      },
      "position": {
        "x": -2.2816052436828613,
        "y": 0.002920885570347309,
        "z": 0.7428364753723145
      },
      "rotation": {
        "x": 0,
        "y": 1.5710148811340332,
        "z": 0
      }
    },
    {
      "class": "nightstand",
      "size": {
        "x": 0.4412340819835663,
        "y": 0.7867294549942017,
        "z": 0.4410477876663208
      },
      "position": {
        "x": -1.52566397190094,
        "y": -0.0011033839546144009,
        "z": -0.5242888927459717
      },
      "rotation": {
        "x": 0,
        "y": 1.5699188709259033,
        "z": 0
      }
    },
    {
      "class": "nightstand",
      "size": {
        "x": 0.4023294746875763,
        "y": 0.6958772540092468,
        "z": 0.4503008723258972
      },
      "position": {
        "x": -1.5294666290283203,
        "y": -0.0034074801951646805,
        "z": 2.1623919010162354
      },
      "rotation": {
        "x": 0,
        "y": 1.571271300315857,
        "z": 0
      }
    },
    {
      "class": "wardrobe",
      "size": {
        "x": 2.2638089656829834,
        "y": 2.467797040939331,
        "z": 0.5607547163963318
      },
      "position": {
        "x": -0.49904173612594604,
        "y": 0.0025298306718468666,
        "z": -2.3918509483337402
      },
      "rotation": {
        "x": 0,
        "y": 0.0024042963050305843,
        "z": 0
      }
    },
    {
      "class": "tv_stand",
      "size": {
        "x": 1.472605586051941,
        "y": 0.4711158573627472,
        "z": 0.35414642095565796
      },
      "position": {
        "x": 2.2794854640960693,
        "y": 0.0058760312385857105,
        "z": 1.0111734867095947
      },
      "rotation": {
        "x": 0,
        "y": -1.5772112607955933,
        "z": 0
      }
    },
    {
      "class": "lamp",
      "size": {
        "x": 0.8013293743133545,
        "y": 0.9612998962402344,
        "z": 0.7419219613075256
      },
      "position": {
        "x": 0.502985417842865,
        "y": 1.8007858991622925,
        "z": 2.9714856147766113
      },
      "rotation": {
        "x": 0,
        "y": -0.0006809255573898554,
        "z": 0
      }
    }
  ]
}